flask_gcp_pubsub/__init__.py
flask_gcp_pubsub/publisher.py
flask_gcp_pubsub/pubsub.py
flask_gcp_pubsub/storage.py
flask_gcp_pubsub-0.2.11.dist-info/LICENSE
flask_gcp_pubsub-0.2.11.dist-info/METADATA
flask_gcp_pubsub-0.2.11.dist-info/WHEEL
flask_gcp_pubsub-0.2.11.dist-info/top_level.txt
flask_gcp_pubsub-0.2.11.dist-info/RECORD
